{
  "pages": [
    {
      "id": "Page1",
      "isDefault": true
    },
    {
      "id": "ghjkl",
      "isDefault": false
    },
    {
      "id": "Page3",
      "isDefault": false
    },
    {
      "id": "Page4",
      "isDefault": false
    },
    {
      "id": "Page5",
      "isDefault": false
    },
    {
      "id": "Page6",
      "isDefault": false
    },
    {
      "id": "Page7",
      "isDefault": false
    },
    {
      "id": "Page8",
      "isDefault": false
    },
    {
      "id": "Page9",
      "isDefault": false
    },
    {
      "id": "Page10",
      "isDefault": false
    },
    {
      "id": "Page11",
      "isDefault": false
    },
    {
      "id": "Page12",
      "isDefault": false
    },
    {
      "id": "Page13",
      "isDefault": false
    }
  ],
  "viewMode": false,
  "appIsExample": false,
  "unreadCommentThreads": 0,
  "color": "#ECECEC",
  "icon": "shirt",
  "unpublishedCustomJSLibs": [
    {
      "uidString": "jsonwebtoken_/libraries/jsonwebtoken@8.5.1.js"
    },
    {
      "uidString": "ExcelJS_regeneratorRuntime_https://cdn.jsdelivr.net/npm/exceljs@4.3.0/dist/exceljs.min.js"
    }
  ],
  "publishedCustomJSLibs": [],
  "evaluationVersion": 2,
  "applicationVersion": 2,
  "collapseInvisibleWidgets": true,
  "isManualUpdate": false,
  "deleted": false
}